bio2bel_entrez/__init__.py
bio2bel_entrez/__main__.py
bio2bel_entrez/cli.py
bio2bel_entrez/cli_utils.py
bio2bel_entrez/constants.py
bio2bel_entrez/homologene_manager.py
bio2bel_entrez/manager.py
bio2bel_entrez/models.py
bio2bel_entrez/parser.py
bio2bel_entrez/web.py
bio2bel_entrez-0.2.2.dist-info/LICENSE
bio2bel_entrez-0.2.2.dist-info/METADATA
bio2bel_entrez-0.2.2.dist-info/WHEEL
bio2bel_entrez-0.2.2.dist-info/entry_points.txt
bio2bel_entrez-0.2.2.dist-info/top_level.txt
bio2bel_entrez-0.2.2.dist-info/RECORD
