Metadata-Version: 2.1
Name: bio2bel-entrez
Version: 0.2.2
Summary: A package for parsing and storing Entrez Gene
Home-page: https://github.com/cthoyt/pyentrez
Author: Charles Tapley Hoyt
Author-email: charles.hoyt@scai.fraunhofer.de
Maintainer: Charles Tapley Hoyt
Maintainer-email: charles.hoyt@scai.fraunhofer.de
License: MIT License
Platform: UNKNOWN
Classifier: Development Status :: 4 - Beta
Classifier: Environment :: Console
Classifier: Intended Audience :: Developers
Classifier: Intended Audience :: Science/Research
Classifier: Operating System :: OS Independent
Classifier: Programming Language :: Python
Classifier: Programming Language :: Python :: 3 :: Only
Classifier: Programming Language :: Python :: 3.6
Classifier: Programming Language :: Python :: 3.7
Classifier: Topic :: Scientific/Engineering :: Bio-Informatics
Classifier: License :: OSI Approved :: MIT License
Requires-Dist: pybel (<0.14.0,>=0.13.0)
Requires-Dist: bio2bel (<0.3.0,>=0.2.0)
Requires-Dist: click
Requires-Dist: pandas
Requires-Dist: sqlalchemy
Requires-Dist: six
Requires-Dist: tqdm
Provides-Extra: docs
Requires-Dist: flask ; extra == 'docs'
Requires-Dist: flask-admin ; extra == 'docs'
Requires-Dist: sphinx ; extra == 'docs'
Requires-Dist: sphinx-rtd-theme ; extra == 'docs'
Requires-Dist: sphinx-click ; extra == 'docs'
Requires-Dist: sphinx-autodoc-typehints ; extra == 'docs'
Provides-Extra: web
Requires-Dist: flask ; extra == 'web'
Requires-Dist: flask-admin ; extra == 'web'
